datafuncs/__init__.py
datafuncs/datafuncs.py
datafuncs-0.3.6.dist-info/LICENSE
datafuncs-0.3.6.dist-info/METADATA
datafuncs-0.3.6.dist-info/WHEEL
datafuncs-0.3.6.dist-info/top_level.txt
datafuncs-0.3.6.dist-info/RECORD
