Metadata-Version: 2.1
Name: datafuncs
Version: 0.3.6
Summary: Functions for Data Processing
Home-page: https://github.com/Liam-Leonard/Data-Funcs
Author: Fraser Woodward and Liam Leonard
Author-email: woodwardfraser1@gmail.com, liamleonard@outlook.ie
Project-URL: Bug Tracker, https://github.com/Liam-Leonard/Data-Funcs/issues
Project-URL: Documentation, https://github.com/Liam-Leonard/Data-Funcs
Classifier: Programming Language :: Python :: 3
Classifier: License :: OSI Approved :: MIT License
Classifier: Operating System :: OS Independent
Requires-Python: >=3.7
License-File: LICENSE
